README.md
setup.cfg
setup.py
moonshot_algo/__init__.py
moonshot_algo/entities.py
moonshot_algo/factories.py
moonshot_algo/models.py
moonshot_algo.egg-info/PKG-INFO
moonshot_algo.egg-info/SOURCES.txt
moonshot_algo.egg-info/dependency_links.txt
moonshot_algo.egg-info/not-zip-safe
moonshot_algo.egg-info/requires.txt
moonshot_algo.egg-info/top_level.txt