Metadata-Version: 1.0
Name: moonshot-algo
Version: 1.0.9
Summary: core python algo
Home-page: https://github.com/moonshot-marketing/algo-py-core
Author: shai kazaz
Author-email: shai@moonshot.co.il
License: UNKNOWN
Platform: UNKNOWN
